---
title: 多线程:synchronized
tags:
- Java
---
<details>
<summary>点击展开目录</summary>
<!-- TOC -->

- [作用](#作用)
- [使用](#使用)
- [原理](#原理)
    - [monitor监视器](#monitor监视器)
- [对synchronized的优化](#对synchronized的优化)
    - [自旋锁](#自旋锁)
    - [锁消除](#锁消除)
    - [锁粗化](#锁粗化)
    - [偏向锁](#偏向锁)
    - [轻量级锁](#轻量级锁)
- [Tips](#tips)
- [Q&A](#qa)
- [参考](#参考)

<!-- /TOC -->
</details>

## 作用

可以修饰方法, 代码块, 确保多个线程在同一个时刻, 只能有一个线程处于方法或者同步块中, 以保证线程对变量访问的可见性和排他性

无论是修饰方法还是代码块都是获取一个对象的监视器(monitor)然后才能进入同步块或者同步方法,

而获取过程是排他的, 也就是说同一时刻只有一个线程获取到由synchronized所保护对象的监视器, 没有获取到的线程就会被阻塞.

保证有序性, 原子性:
* 有序性: 一个代码块或方法, 同一时间只允许一个线程对其进行加锁并执行的操作, 因此多个线程必须串行执行; 同时持有同一锁对象的多个代码块也只能串行执行
* 原子性: 对整个代码块加锁, 同一时刻只有一个线程可以操作, 对于持锁线程, 整个代码块是不可分割的

悲观锁的实现方案

## 使用

同步有几种方式, 分别是什么?

* 同步代码块
* 同步方法

synchronized: 线程同步关键字

```Java
synchronized (锁对象) {
    ....
}
public synchronized void method(){
    ....
}
public static synchronized method(){
    ....
}
```

同步代码块中的锁对象可以是任意的类或对象; 但多个线程时, 要使用同一个锁对象才能够保证线程安全.

当一个线程A使用一个synchronized修饰的方法时, 同步方法中的锁对象是 this, 是对象锁, 其他线程想使用这个方法时就必须等待, 直到线程A 使用完该方法(或线程A使用wait主动让出CUP资源).

当被synchronized限定的代码段执行完, 就释放对象锁(信号量)

静态同步方法中的锁对象是 `类名.class`, 是类锁.

使用synchronized加锁:

* 对于普通变量, 方法所加的锁都是对象锁, 一个对象一把锁, 互不影响
* 对于静态变量, 方法所加的锁都是类锁, 此类的所有对象共用一把锁

> lock可中断, 可超时, 可尝试获取锁

## 原理

同步块 的实现是通过`monitorenter`和`monitorexit`指令

同步方法是依靠方法修饰符上的`ACC_SYNCHRONIZED`来完成的

本质是对一个对象的监视器(monitor)进行获取, 获取过程是排他的.

任一线程对同步域的访问首先要获得对象的监视器, 获取失败就会进入同步队列(synchronizedqueue), 线程也随之进入阻塞(BLOCKED)状态,

当获取到监视器的线程释放了锁, 会唤醒等待的线程, 使其重新尝试获取监视器.

```Java
public synchronized void method1(){
    System.out.println("1");
}
public static synchronized void method2(){
    System.out.println("2");
}

public static void main(String[] args) {
    synchronized (SynchronizeCase.class){
        System.out.println("3");
    }
}
```

```Java
Compiled from "SynchronizeCase.java"
public class SynchronizeCase {
  public SynchronizeCase();
    Code:
       0: aload_0
       1: invokespecial #1                  // Method java/lang/Object."<init>":()V
       4: return

  public synchronized void method1();
    Code:
       0: getstatic     #2                  // Field java/lang/System.out:Ljava/io/PrintStream;
       3: ldc           #3                  // String 1
       5: invokevirtual #4                  // Method java/io/PrintStream.println:(Ljava/lang/String;)V
       8: return

  public static synchronized void method2();
    Code:
       0: getstatic     #2                  // Field java/lang/System.out:Ljava/io/PrintStream;
       3: ldc           #5                  // String 2
       5: invokevirtual #4                  // Method java/io/PrintStream.println:(Ljava/lang/String;)V
       8: return

  public static void main(java.lang.String[]);
    Code:
       0: ldc           #6                  // class SynchronizeCase
       2: dup
       3: astore_1
       4: monitorenter // 进入
       5: getstatic     #2                  // Field java/lang/System.out:Ljava/io/PrintStream;
       8: ldc           #7                  // String 3
      10: invokevirtual #4                  // Method java/io/PrintStream.println:(Ljava/lang/String;)V
      13: aload_1
      14: monitorexit // 退出
      15: goto          23
      18: astore_2
      19: aload_1
      20: monitorexit
      21: aload_2
      22: athrow
      23: return
    Exception table:
       from    to  target type
           5    15    18   any
          18    21    18   any
}
```

**monitorenter指令**
每个对象都与一个monitor 相关联. 当且仅当拥有所有者时(被拥有), monitor才会被锁定. 执行到monitorenter指令的线程, 会尝试去获得对应的monitor, 如下:
1. 每个对象维护着一个记录着被锁次数的计数器, 对象未被锁定时, 该计数器为0. 线程进入monitor(执行monitorenter指令)时, 会把计数器设置为1.
2. 当同一个线程再次获得该对象的锁的时候, 计数器再次自增.
3. 当其他线程想获得该monitor的时候, 就会阻塞, 直到计数器为0才能成功.

**monitorexit指令**
monitor的拥有者线程才能执行 monitorexit指令.
线程执行monitorexit指令, 就会让monitor的计数器减一. 如果计数器为0, 表明该线程不再拥有monitor. 其他线程就允许尝试去获得该monitor了.

**ACC_SYNCHRONIZED标志**
方法级别的同步是隐式的, 作为方法调用的一部分. 同步方法的常量池中会有一个ACC_SYNCHRONIZED标志.
当调用一个设置了ACC_SYNCHRONIZED标志的方法, 执行线程需要先获得monitor锁, 然后开始执行方法, 方法执行之后再释放monitor锁, 当方法不管是正常return还是抛出异常都会释放对应的monitor锁.

在这期间, 如果其他线程来请求执行方法, 会因为无法获得监视器锁而被阻断住.

如果在方法执行过程中, 发生了异常, 并且方法内部并没有处理该异常, 那么在异常被抛到方法外面之前监视器锁会被自动释放.

### monitor监视器


## 对synchronized的优化

锁状态: 无锁状态 -> 偏向锁状态 -> 轻量级锁状态 -> 重量级锁状态

### 自旋锁

适应性自旋锁: 自动调节自旋的次数

### 锁消除

### 锁粗化

### 偏向锁

### 轻量级锁


## Tips

局部变量不会发生线程安全问题.

synchronized支持锁重入

## Q&A

> 锁重入: 自己可以获取自己的内部锁.
>
> 当线程请求一个由其它线程持有的对象锁时, 该线程会阻塞, 而当线程请求由自己持有的对象锁时, 如果该锁是重入锁, 请求就会成功, 否则阻塞

## 参考

